__init__.py
cloudcatalog.py
cloudcatalog-1.1.0.dist-info/licenses/LICENSE.MD
data/README.rst
utils/cloudcatalog_ui.py
utils/recatalog.py
utils/validator.py
cloudcatalog-1.1.0.dist-info/METADATA
cloudcatalog-1.1.0.dist-info/WHEEL
cloudcatalog-1.1.0.dist-info/top_level.txt
cloudcatalog-1.1.0.dist-info/RECORD
