Metadata-Version: 2.4
Name: cloudcatalog
Version: 1.1.0
Summary: API for accessing the generalized CloudCatalog (cloudcatalog) specification for sharing data in and across clouds
Author-email: Johns Hopkins University Applied Physics Laboratory LLC <sandy.antunes@jhuapl.edu>
License: MIT License
Project-URL: Homepage, https://heliocloud.org
Project-URL: Documentation, https://github.com/heliocloud-data/cloudcatalog
Project-URL: Repository, https://github.com/heliocloud-data/cloudcatalog
Keywords: cloud,index,catalog,AWS
Classifier: Development Status :: 4 - Beta
Classifier: Topic :: Utilities
Classifier: License :: OSI Approved :: MIT License
Requires-Python: >=3.9
License-File: LICENSE.MD
Requires-Dist: boto3
Requires-Dist: pandas
Dynamic: license-file
